md_ulb_pwrap-0.1.3.dist-info/METADATA
md_ulb_pwrap-0.1.3.dist-info/WHEEL
md_ulb_pwrap/__init__.py
md_ulb_pwrap/md_ulb_pwrap.cpython-39-x86_64-linux-gnu.so
md_ulb_pwrap-0.1.3.dist-info/RECORD
